WavinSentioModbus/Defaults.py
WavinSentioModbus/ModbusWrapper.py
WavinSentioModbus/SentioApi.py
WavinSentioModbus/SentioBoilerTank.py
WavinSentioModbus/SentioHCC.py
WavinSentioModbus/SentioITC.py
WavinSentioModbus/SentioRegisterMap.py
WavinSentioModbus/SentioRoom.py
WavinSentioModbus/SentioSensors.py
WavinSentioModbus/SentioTypes.py
WavinSentioModbus/__init__.py
wavinsentiomodbus-0.14.0.dist-info/licenses/LICENSE
wavinsentiomodbus-0.14.0.dist-info/METADATA
wavinsentiomodbus-0.14.0.dist-info/WHEEL
wavinsentiomodbus-0.14.0.dist-info/top_level.txt
wavinsentiomodbus-0.14.0.dist-info/RECORD
