Metadata-Version: 2.4
Name: WavinSentioModbus
Version: 0.14.0
Summary: Python API for interfacing with Wavin CCU-208
Home-page: https://github.com/wavingroup/WavinSentioModbus
Author: Wavin T&I
Author-email: support@wavin.com
License: MIT
Classifier: Development Status :: 5 - Production/Stable
Classifier: License :: OSI Approved :: MIT License
Classifier: Programming Language :: Python
License-File: LICENSE
Requires-Dist: pyserial>=3.5
Requires-Dist: pymodbus>=3.11
Dynamic: author
Dynamic: author-email
Dynamic: classifier
Dynamic: description
Dynamic: description-content-type
Dynamic: home-page
Dynamic: license
Dynamic: license-file
Dynamic: requires-dist
Dynamic: summary
